examples/__init__.py
examples/shared_args.py
examples/fashion_mnist/__init__.py
examples/fashion_mnist/shared_args.py
examples/fashion_mnist/pytorch/__init__.py
examples/fashion_mnist/pytorch/train.py
examples/fashion_mnist/pytorch/xla/__init__.py
examples/fashion_mnist/pytorch/xla/train.py
examples/fashion_mnist/tensorflow/__init__.py
examples/fashion_mnist/tensorflow/train.py
examples/hello_world/__init__.py
examples/hello_world/pytorch/__init__.py
examples/hello_world/pytorch/train.py
examples/hello_world/pytorch/train_eager.py
examples/hello_world/pytorch/xla/__init__.py
examples/hello_world/pytorch/xla/train.py
examples/hello_world/tensorflow/__init__.py
examples/hello_world/tensorflow/train.py
examples/hello_world/tensorflow/train_eager.py
examples/legacy/__init__.py
examples/legacy/chatbot/__init__.py
examples/legacy/chatbot/chatbot_data_reference.py
examples/legacy/chatbot/conversation_dataset.py
examples/legacy/chatbot/conversation_parsing.py
examples/legacy/chatbot/shared.py
examples/legacy/chatbot/split_conversations_dataset.py
examples/legacy/chatbot/voc.py
examples/legacy/chatbot/pytorch/__init__.py
examples/legacy/chatbot/pytorch/train_chatbot_reference.py
examples/legacy/chatbot/pytorch/original_chatbot_tutorial/__init__.py
examples/legacy/chatbot/pytorch/original_chatbot_tutorial/chatbot_reference.py
examples/legacy/chatbot/pytorch/original_chatbot_tutorial/chatbot_reference_distributed.py
examples/legacy/chatbot/pytorch/original_chatbot_tutorial/evaluate_reference_chatbot.py
examples/legacy/chatbot/pytorch/original_chatbot_tutorial/evaluation.py
examples/legacy/chatbot/pytorch/original_chatbot_tutorial/loss.py
examples/legacy/chatbot/pytorch/original_chatbot_tutorial/model_data_generation.py
examples/legacy/chatbot/pytorch/original_chatbot_tutorial/seq2seq.py
examples/legacy/chatbot/pytorch/original_chatbot_tutorial/training.py
examples/legacy/chatbot/tensorflow/__init__.py
examples/legacy/chatbot/tensorflow/train_chatbot_reference.py
mlpug-0.1.0.dist-info/LICENSE
mlpug-0.1.0.dist-info/METADATA
mlpug-0.1.0.dist-info/WHEEL
mlpug-0.1.0.dist-info/dependency_links.txt
mlpug-0.1.0.dist-info/top_level.txt
mlpug-0.1.0.dist-info/RECORD
