Metadata-Version: 2.1
Name: mlpug
Version: 0.1.0
Summary: MLPug is a library for training and evaluating Machine Learning (ML) models, able to use different ML libraries as backends.
Home-page: https://github.com/nuhame/mlpug
Author: Freddy Snijder
Author-email: mlpug@visionscapers.com
Classifier: Programming Language :: Python :: 3.9
Classifier: License :: OSI Approved :: Apache Software License
Classifier: Operating System :: OS Independent
Requires-Python: >=3.9
License-File: LICENSE
Requires-Dist: visionscaper-pybase
Requires-Dist: tensorboardX
